hcf_backend/__init__.py
hcf_backend/backend.py
hcf_backend/manager.py
hcf_backend/utils/__init__.py
hcf_backend/utils/crawlmanager.py
hcf_backend/utils/hcfpal.py
hcf_backend-0.6.0.dist-info/licenses/LICENSE
hcf_backend-0.6.0.dist-info/METADATA
hcf_backend-0.6.0.dist-info/WHEEL
hcf_backend-0.6.0.dist-info/top_level.txt
hcf_backend-0.6.0.dist-info/RECORD
