Metadata-Version: 2.4
Name: hcf-backend
Version: 0.6.0
Summary: ScrapyCloud HubStorage frontier backend for Frontera
Home-page: https://github.com/scrapinghub/hcf-backend
Maintainer: Scrapinghub
License: BSD
Classifier: Development Status :: 5 - Production/Stable
Classifier: Intended Audience :: Developers
Classifier: License :: OSI Approved :: BSD License
Classifier: Operating System :: OS Independent
Classifier: Programming Language :: Python :: 3.9
Classifier: Programming Language :: Python :: 3.10
Classifier: Programming Language :: Python :: 3.11
Classifier: Programming Language :: Python :: 3.12
Classifier: Programming Language :: Python :: 3.13
License-File: LICENSE
Requires-Dist: frontera<0.8,>=0.7.2
Requires-Dist: humanize>=0.5.1
Requires-Dist: requests>=2.18.4
Requires-Dist: retrying>=1.3.3
Requires-Dist: scrapinghub>=2.3.1
Requires-Dist: shub-workflow>=1.10.20
Dynamic: classifier
Dynamic: description
Dynamic: description-content-type
Dynamic: home-page
Dynamic: license
Dynamic: license-file
Dynamic: maintainer
Dynamic: requires-dist
Dynamic: summary
